asdfile/ASCII.py
asdfile/ASCIIConstants.py
asdfile/__init__.py
asdfile/asdfile.py
asdfile-0.0.5.dist-info/LICENSE.txt
asdfile-0.0.5.dist-info/METADATA
asdfile-0.0.5.dist-info/WHEEL
asdfile-0.0.5.dist-info/top_level.txt
asdfile-0.0.5.dist-info/RECORD
