Metadata-Version: 2.2
Name: asdfile
Version: 0.0.5
Summary: Flat file format for multi-tabular data storage using ASCII separator characters.
Author: Hemant Nikam
Author-email: nikhemant@gmail.com
License: MIT
License-File: LICENSE.txt
Requires-Dist: pandas
Dynamic: author
Dynamic: author-email
Dynamic: description
Dynamic: description-content-type
Dynamic: license
Dynamic: requires-dist
Dynamic: summary
